tnnt_discordbot_cogs/__init__.py
tnnt_discordbot_cogs/admin.py
tnnt_discordbot_cogs/apps.py
tnnt_discordbot_cogs/auth_hooks.py
tnnt_discordbot_cogs/helper.py
tnnt_discordbot_cogs/cogs/__init__.py
tnnt_discordbot_cogs/cogs/about.py
tnnt_discordbot_cogs/cogs/admin.py
tnnt_discordbot_cogs/cogs/auth.py
tnnt_discordbot_cogs/cogs/locate.py
tnnt_discordbot_cogs/cogs/lookup.py
tnnt_discordbot_cogs/cogs/models.py
tnnt_discordbot_cogs/cogs/price_check.py
tnnt_discordbot_cogs/cogs/recruit_me.py
tnnt_discordbot_cogs/cogs/welcome.py
tnnt_discordbot_cogs/locale/.gitkeep
tnnt_discordbot_cogs/locale/django.pot
tnnt_discordbot_cogs/locale/cs_CZ/LC_MESSAGES/django.po
tnnt_discordbot_cogs/locale/de/LC_MESSAGES/django.mo
tnnt_discordbot_cogs/locale/de/LC_MESSAGES/django.po
tnnt_discordbot_cogs/locale/es/LC_MESSAGES/django.mo
tnnt_discordbot_cogs/locale/es/LC_MESSAGES/django.po
tnnt_discordbot_cogs/locale/fr_FR/LC_MESSAGES/django.mo
tnnt_discordbot_cogs/locale/fr_FR/LC_MESSAGES/django.po
tnnt_discordbot_cogs/locale/it_IT/LC_MESSAGES/django.po
tnnt_discordbot_cogs/locale/ja/LC_MESSAGES/django.po
tnnt_discordbot_cogs/locale/ko_KR/LC_MESSAGES/django.mo
tnnt_discordbot_cogs/locale/ko_KR/LC_MESSAGES/django.po
tnnt_discordbot_cogs/locale/nl_NL/LC_MESSAGES/django.po
tnnt_discordbot_cogs/locale/pl_PL/LC_MESSAGES/django.po
tnnt_discordbot_cogs/locale/ru/LC_MESSAGES/django.mo
tnnt_discordbot_cogs/locale/ru/LC_MESSAGES/django.po
tnnt_discordbot_cogs/locale/sk/LC_MESSAGES/django.po
tnnt_discordbot_cogs/locale/uk/LC_MESSAGES/django.mo
tnnt_discordbot_cogs/locale/uk/LC_MESSAGES/django.po
tnnt_discordbot_cogs/locale/zh_Hans/LC_MESSAGES/django.mo
tnnt_discordbot_cogs/locale/zh_Hans/LC_MESSAGES/django.po
tnnt_discordbot_cogs/migrations/0001_initial.py
tnnt_discordbot_cogs/migrations/0002_setting_lookup_channels.py
tnnt_discordbot_cogs/migrations/0003_setting_locate_channels.py
tnnt_discordbot_cogs/migrations/0004_permission.py
tnnt_discordbot_cogs/migrations/__init__.py
tnnt_discordbot_cogs-1.0.1.dist-info/METADATA
tnnt_discordbot_cogs-1.0.1.dist-info/WHEEL
tnnt_discordbot_cogs-1.0.1.dist-info/licenses/LICENSE
tnnt_discordbot_cogs-1.0.1.dist-info/RECORD
