Metadata-Version: 2.4
Name: tnnt-discordbot-cogs
Version: 1.0.1
Summary: TN-NT customized cogs for aa-discordbot
Project-URL: Changelog, https://github.com/terra-nanotech/tn-nt-discordbot-cogs/blob/master/CHANGELOG.md
Project-URL: Documentation, https://github.com/terra-nanotech/tn-nt-discordbot-cogs/blob/master/README.md
Project-URL: Homepage, https://github.com/terra-nanotech/tn-nt-discordbot-cogs
Project-URL: Tracker, https://github.com/terra-nanotech/tn-nt-discordbot-cogs/issues
Author-email: Peter Pfeufer <develop@ppfeufer.de>
License:                     GNU GENERAL PUBLIC LICENSE
License-File: LICENSE
Keywords: allianceauth,discord,eveonline,terra_nanotech
Classifier: Environment :: Web Environment
Classifier: Framework :: Django
Classifier: Framework :: Django :: 4.0
Classifier: Intended Audience :: Developers
Classifier: License :: OSI Approved :: GNU General Public License v3 (GPLv3)
Classifier: Operating System :: OS Independent
Classifier: Programming Language :: Python
Classifier: Programming Language :: Python :: 3 :: Only
Classifier: Programming Language :: Python :: 3.10
Classifier: Programming Language :: Python :: 3.11
Classifier: Programming Language :: Python :: 3.12
Classifier: Programming Language :: Python :: 3.13
Classifier: Topic :: Internet :: WWW/HTTP
Classifier: Topic :: Internet :: WWW/HTTP :: Dynamic Content
Requires-Python: <3.14,>=3.10
Requires-Dist: allianceauth-app-utils>=1.14.1
Requires-Dist: allianceauth-discordbot
Requires-Dist: allianceauth<5,>=3
Requires-Dist: django-eveuniverse>=1.3
